tornado_console/__about__.py
tornado_console/__init__.py
tornado_console/compat.py
tornado_console-1.0.0.dist-info/DESCRIPTION.rst
tornado_console-1.0.0.dist-info/METADATA
tornado_console-1.0.0.dist-info/RECORD
tornado_console-1.0.0.dist-info/WHEEL
tornado_console-1.0.0.dist-info/metadata.json
tornado_console-1.0.0.dist-info/top_level.txt
