Metadata-Version: 2.0
Name: tornado-console
Version: 1.0.0
Summary: Python interactive console running alongside your Tornado application - very
Requires-Dist: Tornado
